yzytk/__init__.py
yzytk/config.py
yzytk/img/--.png
yzytk/img/-o.png
yzytk/img/icon.png
yzytk/img/none.png
yzytk/img/x-.png
yzytk/img/xo.png
yzytk/img/music/pause.png
yzytk/img/music/play.png
yzytk-2.0.20220919.dist-info/METADATA
yzytk-2.0.20220919.dist-info/WHEEL
yzytk-2.0.20220919.dist-info/top_level.txt
yzytk-2.0.20220919.dist-info/RECORD
